segmentation_experimentation/__init__.py
segmentation_experimentation/experiment.py
segmentation_experimentation/logger.py
segmentation_experimentation/yolo_model.py
segmentation_experimentation-0.0.4.dist-info/METADATA
segmentation_experimentation-0.0.4.dist-info/WHEEL
segmentation_experimentation-0.0.4.dist-info/licenses/LICENSE
segmentation_experimentation-0.0.4.dist-info/RECORD
